zwppt_mcp/__init__.py
zwppt_mcp/server.py
zwppt_mcp-0.0.3.dist-info/licenses/LICENSE
zwppt_mcp-0.0.3.dist-info/METADATA
zwppt_mcp-0.0.3.dist-info/WHEEL
zwppt_mcp-0.0.3.dist-info/entry_points.txt
zwppt_mcp-0.0.3.dist-info/top_level.txt
zwppt_mcp-0.0.3.dist-info/RECORD
